awesome_audit_log/__init__.py
awesome_audit_log/apps.py
awesome_audit_log/conf.py
awesome_audit_log/context.py
awesome_audit_log/db.py
awesome_audit_log/management/__init__.py
awesome_audit_log/management/commands/__init__.py
awesome_audit_log/management/commands/migrate_audit_timestamps.py
awesome_audit_log/middleware.py
awesome_audit_log/signals.py
awesome_audit_log/tasks.py
awesome_audit_log/utils.py
awesome_audit_log_django-1.0.0.dist-info/METADATA
awesome_audit_log_django-1.0.0.dist-info/WHEEL
awesome_audit_log_django-1.0.0.dist-info/licenses/LICENSE
awesome_audit_log_django-1.0.0.dist-info/RECORD
