Metadata-Version: 2.4
Name: awesome-audit-log-django
Version: 1.0.0
Summary: Per-model audit logs to TABLENAME_log with entry-point capture (HTTP/management/shell/celery)
License: MIT
License-File: LICENSE
Keywords: django,audit,logging,audit-log,log,changes,databse-changes
Author: AmooAti
Author-email: adhamiamirhossein@gmail.com
Requires-Python: >=3.10,<3.14
Classifier: Framework :: Django
Classifier: Framework :: Django :: 4.2
Classifier: Framework :: Django :: 5
Classifier: Framework :: Django :: 5.0
Classifier: Framework :: Django :: 5.1
Classifier: Framework :: Django :: 5.2
Classifier: License :: OSI Approved :: MIT License
Classifier: Programming Language :: Python
Classifier: Programming Language :: Python :: 3
Classifier: Programming Language :: Python :: 3.10
Classifier: Programming Language :: Python :: 3.11
Classifier: Programming Language :: Python :: 3.12
Classifier: Programming Language :: Python :: 3.13
Classifier: Programming Language :: Python :: 3 :: Only
Requires-Dist: Django (>=4.2)
Project-URL: Homepage, https://github.com/AmooAti/awesome-audit-log-django
Project-URL: Repository, https://github.com/AmooAti/awesome-audit-log-django
